[
    {
        "name": "Telepizza",
        "location": {
            "city": "Barcelona",
            "country": "Spain",
            "environment": "Seaside"
        },
        "dishes": ["Pizza", "Steak", "Bread", "Soup"],
        "specialty": "BBQ pizza",
        "ambience": "average",
        "nationality": "american",
        "qualification": 1,
        "criticReview": "The pizza was good",
        "peopleCapacity": 100,
        "peopleInside": 50,
        "averagePrice": 10,
        "dresscode": "casual"

    },
    {
        "name": "Tagliatella",
        "location": {
            "city": "Mataro",
            "country": "Spain",
            "environment": "Centric"
        },
        "dishes": ["Lettuce", "Pasta", "Steak"],
        "specialty": "Pasta alla marinera",
        "ambience": "chill",
        "nationality": "italian",
        "qualification": 2,
        "criticReview": "The pasta was good",
        "peopleCapacity": 50,
        "peopleInside": 30,
        "averagePrice": 15,
        "dresscode": "formal"
    },
    {
        "name": "McDonalds",
        "location": {
            "city": "Mataro",
            "country": "Spain",
            "environment": "Mountain"
        },
        "dishes": ["Steak", "Fish", "Hamburger"],
        "specialty": "Burger",
        "ambience": "familiar",
        "nationality": "american",
        "qualification": 1,
        "criticReview": "The burger was good",
        "peopleCapacity": 200,
        "peopleInside": 100,
        "averagePrice": 5,
        "dresscode": "very casual"
    },
    {
        "name": "Pans",
        "location": {
            "city": "Rupit",
            "country": "Spain",
            "environment": "Village"
        },
        "dishes": ["Sandwich", "Nuggets", "Pizza"],
        "specialty": "Veggie sandwich",
        "ambience": "average",
        "nationality": "french",
        "qualification": 3,
        "criticReview": "The sandwich was good",
        "peopleCapacity": 30,
        "peopleInside": 20,
        "averagePrice": 7,
        "dresscode": "casual"
    },
    {
        "name": "Giovesse",
        "location": {
            "city": "London",
            "country": "UK",
            "environment": "Centric"
        },
        "dishes": ["Pizza", "Tacos", "Sausages"],
        "specialty": "Sausage roll",
        "ambience": "fancy",
        "nationality": "french",
        "qualification": 4,
        "criticReview": "The sausage was good",
        "peopleCapacity": 100,
        "peopleInside": 52,
        "averagePrice": 20,
        "dresscode": "very formal"
    },
    {
        "name": "Fosters",
        "location": {
            "city": "Barcares",
            "country": "France",
            "environment": "Village"
        },
        "dishes": ["Paella", "Chicken", "Sushi"],
        "specialty": "Roasted wings",
        "ambience": "country",
        "nationality": "american",
        "qualification": 3,
        "criticReview": "The wings were good",
        "peopleCapacity": 60,
        "peopleInside": 22,
        "averagePrice": 15,
        "dresscode": "casual"
    },
    {
        "name": "Tagliatella",
        "location": {
            "city": "Escala",
            "country": "Spain",
            "environment": "Seaside"
        },
        "dishes": ["Lettuce", "Pasta", "Steak"],
        "specialty": "Pasta alla marinera",
        "ambience": "chill",
        "nationality": "italian",
        "qualification": 1,
        "criticReview": "The pasta was not good",
        "peopleCapacity": 50,
        "peopleInside": 32,
        "averagePrice": 15,
        "dresscode": "formal"
    }
]
